shape_generator/__init__.py
shape_generator/example_cross_sections.py
shape_generator/helpers.py
shape_generator/shape_generator.py
shape_generator/shape_generator_holding.py
shape_generator/swmm_predefined.py
shape_generator/swmm_std_cross_section_curves.json
SWMM_xsections_shape_generator-0.7.post2.dist-info/LICENSE
SWMM_xsections_shape_generator-0.7.post2.dist-info/METADATA
SWMM_xsections_shape_generator-0.7.post2.dist-info/WHEEL
SWMM_xsections_shape_generator-0.7.post2.dist-info/top_level.txt
SWMM_xsections_shape_generator-0.7.post2.dist-info/RECORD
