Metadata-Version: 2.1
Name: SWMM-xsections-shape-generator
Version: 0.7.post2
Summary: US-EPA SWMM Cross-Section curve shape generator
Home-page: https://github.com/MarkusPic/SWMM_xsections_shape_generator
Author: Markus Pichler
Author-email: markus.pichler@tugraz.at
License: MIT
Project-URL: Documentation, https://markuspic.github.io/SWMM_xsections_shape_generator/
Keywords: swmm,environment,civil_engineering,api
Classifier: Programming Language :: Python :: 3
Classifier: License :: OSI Approved :: MIT License
Classifier: Operating System :: OS Independent
Classifier: Topic :: Scientific/Engineering
Classifier: Topic :: Scientific/Engineering :: Hydrology
Classifier: Topic :: Software Development :: Libraries
Classifier: Topic :: Software Development :: Libraries :: Application Frameworks
Classifier: Development Status :: 3 - Alpha
Classifier: Intended Audience :: Science/Research
Classifier: Natural Language :: English
Requires-Python: >=3.6
License-File: LICENSE
Requires-Dist: numpy
Provides-Extra: matplotlib
Requires-Dist: matplotlib ; extra == 'matplotlib'
Provides-Extra: pandas
Requires-Dist: pandas ; extra == 'pandas'
Provides-Extra: swmm-api
Requires-Dist: swmm-api (>=0.3) ; extra == 'swmm-api'
Provides-Extra: sympy
Requires-Dist: sympy ; extra == 'sympy'
